motest/README.md
motest/__main__.py
motest-0.1.1.dist-info/METADATA
motest-0.1.1.dist-info/WHEEL
motest-0.1.1.dist-info/entry_points.txt
motest-0.1.1.dist-info/licenses/LICENSE
motest-0.1.1.dist-info/RECORD
