Metadata-Version: 2.4
Name: motest
Version: 0.1.1
Summary: Small cli that allows for more elborate testing inside Marimo
Project-URL: repository, https://github.com/koaning/motest
Project-URL: issue-tracker, https://github.com/koaning/motest/issues
Project-URL: documentation, https://koaning.github.io/motest/
Author: Vincent D. Warmerdam
License: MIT License
License-File: LICENSE
Classifier: License :: OSI Approved :: MIT License
Classifier: Programming Language :: Python :: 3
Classifier: Programming Language :: Python :: 3.10
Classifier: Programming Language :: Python :: 3.11
Classifier: Programming Language :: Python :: 3.12
Classifier: Topic :: Scientific/Engineering
Classifier: Topic :: Software Development :: Libraries :: Python Modules
Requires-Dist: marimo
Requires-Dist: pytest
